jameswebb_archiver/__init__.py
jameswebb_archiver/__main__.py
jameswebb_archiver-1.0.0.dist-info/LICENSE
jameswebb_archiver-1.0.0.dist-info/METADATA
jameswebb_archiver-1.0.0.dist-info/WHEEL
jameswebb_archiver-1.0.0.dist-info/entry_points.txt
jameswebb_archiver-1.0.0.dist-info/top_level.txt
jameswebb_archiver-1.0.0.dist-info/RECORD
