Metadata-Version: 2.1
Name: jameswebb-archiver
Version: 1.0.0
Summary: Archives James Webb Telescope's Near Infrared Camera (NIRCam) Images including metdata
Home-page: https://github.com/uraid/jameswebb_archiver
Author: Yair Mizrahi
License: MIT License        
Project-URL: Homepage, https://github.com/uraid/jameswebb_archiver
Classifier: License :: OSI Approved :: MIT License
Classifier: Programming Language :: Python
Classifier: Programming Language :: Python :: 3
Requires-Python: >=3.6
License-File: LICENSE
Requires-Dist: requests
Requires-Dist: beautifulsoup4
